fuckoff_shutdown/__main__.py
fuckoff_shutdown-0.2.0.dist-info/METADATA
fuckoff_shutdown-0.2.0.dist-info/WHEEL
fuckoff_shutdown-0.2.0.dist-info/RECORD
