Metadata-Version: 2.1
Name: fuckoff-shutdown
Version: 0.2.0
Summary: 
Author: megahomyak
Author-email: g.megahomyak@gmail.com
Requires-Python: >=3.8,<4.0
Classifier: Programming Language :: Python :: 3
Classifier: Programming Language :: Python :: 3.8
Classifier: Programming Language :: Python :: 3.9
Classifier: Programming Language :: Python :: 3.10
Classifier: Programming Language :: Python :: 3.11
Classifier: Programming Language :: Python :: 3.12
Requires-Dist: cross-platform-shutdown (>=0.2.0,<0.3.0)
Requires-Dist: fuckoff (>=0.2.0,<0.3.0)
